TosKeriser-0.2.3.dist-info/METADATA
TosKeriser-0.2.3.dist-info/RECORD
TosKeriser-0.2.3.dist-info/WHEEL
TosKeriser-0.2.3.dist-info/entry_points.txt
TosKeriser-0.2.3.dist-info/top_level.txt
toskeriser/__init__.py
toskeriser/completer.py
toskeriser/exceptions.py
toskeriser/helper.py
toskeriser/merger.py
toskeriser/requester.py
toskeriser/toskeriser.py
toskeriser/ui.py
toskeriser/validator.py
usr/share/toskeriser/tosker-types.yaml
usr/share/toskeriser/examples/thinking.csar
