Metadata-Version: 2.1
Name: TosKeriser
Version: 0.2.3
Summary: A tool to complete TosKer application description withsuitable Docker Images
Home-page: https://github.com/di-unipi-socc/TosKeriser
Author: lucarin91
Author-email: to@lucar.in
License: MIT
Keywords: Docker match matcher TOSCA deployment complete development
Platform: UNKNOWN
Classifier: Development Status :: 3 - Alpha
Classifier: Environment :: Console
Classifier: Intended Audience :: Developers
Classifier: Topic :: System :: Installation/Setup
Classifier: License :: OSI Approved :: MIT License
Classifier: Operating System :: POSIX :: Linux
Classifier: Programming Language :: Python :: 2
Classifier: Programming Language :: Python :: 2.7
Classifier: Programming Language :: Python :: 3
Classifier: Programming Language :: Python :: 3.4
Classifier: Programming Language :: Python :: 3.5
Classifier: Programming Language :: Python :: 3.6
Requires-Python: >=2.7, !=3.0.*, !=3.1.*, !=3.2.*, !=3.3.*
Provides-Extra: test
Provides-Extra: dev
Requires-Dist: cmd2 (<=0.8.6)
Requires-Dist: tosca-parser
Requires-Dist: six
Requires-Dist: requests
Requires-Dist: ruamel.yaml
Provides-Extra: dev
Requires-Dist: check-manifest; extra == 'dev'
Requires-Dist: isort; extra == 'dev'
Requires-Dist: flake8; extra == 'dev'
Requires-Dist: tox; extra == 'dev'
Requires-Dist: coverage; extra == 'dev'
Provides-Extra: test
Requires-Dist: requests-mock; extra == 'test'
